formlessness/__init__.py
formlessness/base_classes.py
formlessness/constraints.py
formlessness/deserializers.py
formlessness/displayers.py
formlessness/exceptions.py
formlessness/fields.py
formlessness/forms.py
formlessness/sections.py
formlessness/serializers.py
formlessness/types.py
formlessness/utils.py
formlessness/widgets.py
formlessness-0.1.0.dist-info/LICENSE.txt
formlessness-0.1.0.dist-info/WHEEL
formlessness-0.1.0.dist-info/METADATA
formlessness-0.1.0.dist-info/RECORD
