Metadata-Version: 2.1
Name: formlessness
Version: 0.1.0
Summary: 
Author: Travis Jungroth
Author-email: jungroth@gmail.com
Requires-Python: >=3.9,<4.0
Classifier: Programming Language :: Python :: 3
Classifier: Programming Language :: Python :: 3.10
Classifier: Programming Language :: Python :: 3.9
Requires-Dist: pytest-cov (>=3.0.0,<4.0.0)
